MANIFEST.in
README.md
setup.cfg
setup.py
nani_fighter/__init__.py
nani_fighter/the_beginning.py
nani_fighter/the_second_visit.py
nani_fighter.egg-info/PKG-INFO
nani_fighter.egg-info/SOURCES.txt
nani_fighter.egg-info/dependency_links.txt
nani_fighter.egg-info/entry_points.txt
nani_fighter.egg-info/requires.txt
nani_fighter.egg-info/top_level.txt
nani_fighter/res/EA FIFA 2012.mid
nani_fighter/res/EA FIFA 2012.ogg
nani_fighter/res/EXPLODE.wav
nani_fighter/res/ScoreBook.txt
nani_fighter/res/about.png
nani_fighter/res/aboutTNF.png
nani_fighter/res/atel.png
nani_fighter/res/atel2.png
nani_fighter/res/backImage.png
nani_fighter/res/blast.png
nani_fighter/res/booksave1.png
nani_fighter/res/booksave2.png
nani_fighter/res/booksave3.png
nani_fighter/res/bookshoot1.png
nani_fighter/res/bookshoot2.png
nani_fighter/res/bottle.png
nani_fighter/res/bottleMan1.png
nani_fighter/res/bottleMan2.png
nani_fighter/res/bottleMan21.png
nani_fighter/res/bottleMan22.png
nani_fighter/res/bottleManStand.png
nani_fighter/res/chimes.wav
nani_fighter/res/continue.png
nani_fighter/res/crash.png
nani_fighter/res/egg.png
nani_fighter/res/exit.png
nani_fighter/res/exitYesNo.png
nani_fighter/res/fooss.wav
nani_fighter/res/gameicon.png
nani_fighter/res/gameover.png
nani_fighter/res/giveCTwarnLOW.png
nani_fighter/res/helpTNF.png
nani_fighter/res/highScore.png
nani_fighter/res/home.png
nani_fighter/res/house_lo.wav
nani_fighter/res/instruction.png
nani_fighter/res/joy.wav
nani_fighter/res/man_laughing.wav
nani_fighter/res/naniDrink.png
nani_fighter/res/naniFace.png
nani_fighter/res/naniFront.png
nani_fighter/res/naniHand.png
nani_fighter/res/naniHandMarker.png
nani_fighter/res/naniRight.png
nani_fighter/res/newGameWarn.png
nani_fighter/res/pauseImage1.png
nani_fighter/res/pauseImage2.png
nani_fighter/res/player1.png
nani_fighter/res/player2.png
nani_fighter/res/punch.wav
nani_fighter/res/secosmic_lo.wav
nani_fighter/res/sirBody.png
nani_fighter/res/sirHead.png
nani_fighter/res/smoke.png
nani_fighter/res/start.png
nani_fighter/res/win.png
nani_fighter/res/womanScream.wav