Metadata-Version: 1.1
Name: nani-fighter
Version: 1.3.1
Summary: A Simple Game
Home-page: https://github.com/frrahat/Nani-Fighter
Author: Fazle Rahat
Author-email: fr.rahat@gmail.com
License: MIT
Download-URL: https://github.com/frrahat/Nani-Fighter/archive/1.3.1.tar.gz
Keywords: game,school,shooting
Platform: UNKNOWN
Classifier: Intended Audience :: End Users/Desktop
Classifier: License :: OSI Approved :: MIT License
Classifier: Programming Language :: Python
Classifier: Programming Language :: Python :: 2
Classifier: Programming Language :: Python :: 3
